[{"model": "auth.permission", "pk": 1, "fields": {"name": "Can add log entry", "content_type": 1, "codename": "add_logentry"}}, {"model": "auth.permission", "pk": 2, "fields": {"name": "Can change log entry", "content_type": 1, "codename": "change_logentry"}}, {"model": "auth.permission", "pk": 3, "fields": {"name": "Can delete log entry", "content_type": 1, "codename": "delete_logentry"}}, {"model": "auth.permission", "pk": 4, "fields": {"name": "Can view log entry", "content_type": 1, "codename": "view_logentry"}}, {"model": "auth.permission", "pk": 5, "fields": {"name": "Can add permission", "content_type": 2, "codename": "add_permission"}}, {"model": "auth.permission", "pk": 6, "fields": {"name": "Can change permission", "content_type": 2, "codename": "change_permission"}}, {"model": "auth.permission", "pk": 7, "fields": {"name": "Can delete permission", "content_type": 2, "codename": "delete_permission"}}, {"model": "auth.permission", "pk": 8, "fields": {"name": "Can view permission", "content_type": 2, "codename": "view_permission"}}, {"model": "auth.permission", "pk": 9, "fields": {"name": "Can add group", "content_type": 3, "codename": "add_group"}}, {"model": "auth.permission", "pk": 10, "fields": {"name": "Can change group", "content_type": 3, "codename": "change_group"}}, {"model": "auth.permission", "pk": 11, "fields": {"name": "Can delete group", "content_type": 3, "codename": "delete_group"}}, {"model": "auth.permission", "pk": 12, "fields": {"name": "Can view group", "content_type": 3, "codename": "view_group"}}, {"model": "auth.permission", "pk": 13, "fields": {"name": "Can add content type", "content_type": 4, "codename": "add_contenttype"}}, {"model": "auth.permission", "pk": 14, "fields": {"name": "Can change content type", "content_type": 4, "codename": "change_contenttype"}}, {"model": "auth.permission", "pk": 15, "fields": {"name": "Can delete content type", "content_type": 4, "codename": "delete_contenttype"}}, {"model": "auth.permission", "pk": 16, "fields": {"name": "Can view content type", "content_type": 4, "codename": "view_contenttype"}}, {"model": "auth.permission", "pk": 17, "fields": {"name": "Can add session", "content_type": 5, "codename": "add_session"}}, {"model": "auth.permission", "pk": 18, "fields": {"name": "Can change session", "content_type": 5, "codename": "change_session"}}, {"model": "auth.permission", "pk": 19, "fields": {"name": "Can delete session", "content_type": 5, "codename": "delete_session"}}, {"model": "auth.permission", "pk": 20, "fields": {"name": "Can view session", "content_type": 5, "codename": "view_session"}}, {"model": "auth.permission", "pk": 21, "fields": {"name": "Can add custom user", "content_type": 6, "codename": "add_customuser"}}, {"model": "auth.permission", "pk": 22, "fields": {"name": "Can change custom user", "content_type": 6, "codename": "change_customuser"}}, {"model": "auth.permission", "pk": 23, "fields": {"name": "Can delete custom user", "content_type": 6, "codename": "delete_customuser"}}, {"model": "auth.permission", "pk": 24, "fields": {"name": "Can view custom user", "content_type": 6, "codename": "view_customuser"}}, {"model": "auth.permission", "pk": 25, "fields": {"name": "Can add account", "content_type": 7, "codename": "add_account"}}, {"model": "auth.permission", "pk": 26, "fields": {"name": "Can change account", "content_type": 7, "codename": "change_account"}}, {"model": "auth.permission", "pk": 27, "fields": {"name": "Can delete account", "content_type": 7, "codename": "delete_account"}}, {"model": "auth.permission", "pk": 28, "fields": {"name": "Can view account", "content_type": 7, "codename": "view_account"}}, {"model": "auth.permission", "pk": 29, "fields": {"name": "Can add messagechats", "content_type": 8, "codename": "add_messagechats"}}, {"model": "auth.permission", "pk": 30, "fields": {"name": "Can change messagechats", "content_type": 8, "codename": "change_messagechats"}}, {"model": "auth.permission", "pk": 31, "fields": {"name": "Can delete messagechats", "content_type": 8, "codename": "delete_messagechats"}}, {"model": "auth.permission", "pk": 32, "fields": {"name": "Can view messagechats", "content_type": 8, "codename": "view_messagechats"}}, {"model": "auth.permission", "pk": 33, "fields": {"name": "Can add address", "content_type": 9, "codename": "add_address"}}, {"model": "auth.permission", "pk": 34, "fields": {"name": "Can change address", "content_type": 9, "codename": "change_address"}}, {"model": "auth.permission", "pk": 35, "fields": {"name": "Can delete address", "content_type": 9, "codename": "delete_address"}}, {"model": "auth.permission", "pk": 36, "fields": {"name": "Can view address", "content_type": 9, "codename": "view_address"}}, {"model": "auth.permission", "pk": 37, "fields": {"name": "Can add approved uids", "content_type": 10, "codename": "add_approveduids"}}, {"model": "auth.permission", "pk": 38, "fields": {"name": "Can change approved uids", "content_type": 10, "codename": "change_approveduids"}}, {"model": "auth.permission", "pk": 39, "fields": {"name": "Can delete approved uids", "content_type": 10, "codename": "delete_approveduids"}}, {"model": "auth.permission", "pk": 40, "fields": {"name": "Can view approved uids", "content_type": 10, "codename": "view_approveduids"}}, {"model": "auth.permission", "pk": 41, "fields": {"name": "Can add basic info", "content_type": 11, "codename": "add_basicinfo"}}, {"model": "auth.permission", "pk": 42, "fields": {"name": "Can change basic info", "content_type": 11, "codename": "change_basicinfo"}}, {"model": "auth.permission", "pk": 43, "fields": {"name": "Can delete basic info", "content_type": 11, "codename": "delete_basicinfo"}}, {"model": "auth.permission", "pk": 44, "fields": {"name": "Can view basic info", "content_type": 11, "codename": "view_basicinfo"}}, {"model": "auth.permission", "pk": 45, "fields": {"name": "Can add comment", "content_type": 12, "codename": "add_comment"}}, {"model": "auth.permission", "pk": 46, "fields": {"name": "Can change comment", "content_type": 12, "codename": "change_comment"}}, {"model": "auth.permission", "pk": 47, "fields": {"name": "Can delete comment", "content_type": 12, "codename": "delete_comment"}}, {"model": "auth.permission", "pk": 48, "fields": {"name": "Can view comment", "content_type": 12, "codename": "view_comment"}}, {"model": "auth.permission", "pk": 49, "fields": {"name": "Can add contact info", "content_type": 13, "codename": "add_contactinfo"}}, {"model": "auth.permission", "pk": 50, "fields": {"name": "Can change contact info", "content_type": 13, "codename": "change_contactinfo"}}, {"model": "auth.permission", "pk": 51, "fields": {"name": "Can delete contact info", "content_type": 13, "codename": "delete_contactinfo"}}, {"model": "auth.permission", "pk": 52, "fields": {"name": "Can view contact info", "content_type": 13, "codename": "view_contactinfo"}}, {"model": "auth.permission", "pk": 53, "fields": {"name": "Can add uid", "content_type": 14, "codename": "add_uid"}}, {"model": "auth.permission", "pk": 54, "fields": {"name": "Can change uid", "content_type": 14, "codename": "change_uid"}}, {"model": "auth.permission", "pk": 55, "fields": {"name": "Can delete uid", "content_type": 14, "codename": "delete_uid"}}, {"model": "auth.permission", "pk": 56, "fields": {"name": "Can view uid", "content_type": 14, "codename": "view_uid"}}, {"model": "auth.permission", "pk": 57, "fields": {"name": "Can add location info", "content_type": 15, "codename": "add_locationinfo"}}, {"model": "auth.permission", "pk": 58, "fields": {"name": "Can change location info", "content_type": 15, "codename": "change_locationinfo"}}, {"model": "auth.permission", "pk": 59, "fields": {"name": "Can delete location info", "content_type": 15, "codename": "delete_locationinfo"}}, {"model": "auth.permission", "pk": 60, "fields": {"name": "Can view location info", "content_type": 15, "codename": "view_locationinfo"}}, {"model": "auth.permission", "pk": 61, "fields": {"name": "Can add image file", "content_type": 16, "codename": "add_imagefile"}}, {"model": "auth.permission", "pk": 62, "fields": {"name": "Can change image file", "content_type": 16, "codename": "change_imagefile"}}, {"model": "auth.permission", "pk": 63, "fields": {"name": "Can delete image file", "content_type": 16, "codename": "delete_imagefile"}}, {"model": "auth.permission", "pk": 64, "fields": {"name": "Can view image file", "content_type": 16, "codename": "view_imagefile"}}, {"model": "auth.permission", "pk": 65, "fields": {"name": "Can add five review", "content_type": 17, "codename": "add_fivereview"}}, {"model": "auth.permission", "pk": 66, "fields": {"name": "Can change five review", "content_type": 17, "codename": "change_fivereview"}}, {"model": "auth.permission", "pk": 67, "fields": {"name": "Can delete five review", "content_type": 17, "codename": "delete_fivereview"}}, {"model": "auth.permission", "pk": 68, "fields": {"name": "Can view five review", "content_type": 17, "codename": "view_fivereview"}}, {"model": "auth.permission", "pk": 69, "fields": {"name": "Can add detailed info", "content_type": 18, "codename": "add_detailedinfo"}}, {"model": "auth.permission", "pk": 70, "fields": {"name": "Can change detailed info", "content_type": 18, "codename": "change_detailedinfo"}}, {"model": "auth.permission", "pk": 71, "fields": {"name": "Can delete detailed info", "content_type": 18, "codename": "delete_detailedinfo"}}, {"model": "auth.permission", "pk": 72, "fields": {"name": "Can view detailed info", "content_type": 18, "codename": "view_detailedinfo"}}, {"model": "auth.permission", "pk": 73, "fields": {"name": "Can add customer care", "content_type": 19, "codename": "add_customercare"}}, {"model": "auth.permission", "pk": 74, "fields": {"name": "Can change customer care", "content_type": 19, "codename": "change_customercare"}}, {"model": "auth.permission", "pk": 75, "fields": {"name": "Can delete customer care", "content_type": 19, "codename": "delete_customercare"}}, {"model": "auth.permission", "pk": 76, "fields": {"name": "Can view customer care", "content_type": 19, "codename": "view_customercare"}}, {"model": "contenttypes.contenttype", "pk": 1, "fields": {"app_label": "admin", "model": "logentry"}}, {"model": "contenttypes.contenttype", "pk": 2, "fields": {"app_label": "auth", "model": "permission"}}, {"model": "contenttypes.contenttype", "pk": 3, "fields": {"app_label": "auth", "model": "group"}}, {"model": "contenttypes.contenttype", "pk": 4, "fields": {"app_label": "contenttypes", "model": "contenttype"}}, {"model": "contenttypes.contenttype", "pk": 5, "fields": {"app_label": "sessions", "model": "session"}}, {"model": "contenttypes.contenttype", "pk": 6, "fields": {"app_label": "users", "model": "customuser"}}, {"model": "contenttypes.contenttype", "pk": 7, "fields": {"app_label": "users", "model": "account"}}, {"model": "contenttypes.contenttype", "pk": 8, "fields": {"app_label": "chats", "model": "messagechats"}}, {"model": "contenttypes.contenttype", "pk": 9, "fields": {"app_label": "property", "model": "address"}}, {"model": "contenttypes.contenttype", "pk": 10, "fields": {"app_label": "property", "model": "approveduids"}}, {"model": "contenttypes.contenttype", "pk": 11, "fields": {"app_label": "property", "model": "basicinfo"}}, {"model": "contenttypes.contenttype", "pk": 12, "fields": {"app_label": "property", "model": "comment"}}, {"model": "contenttypes.contenttype", "pk": 13, "fields": {"app_label": "property", "model": "contactinfo"}}, {"model": "contenttypes.contenttype", "pk": 14, "fields": {"app_label": "property", "model": "uid"}}, {"model": "contenttypes.contenttype", "pk": 15, "fields": {"app_label": "property", "model": "locationinfo"}}, {"model": "contenttypes.contenttype", "pk": 16, "fields": {"app_label": "property", "model": "imagefile"}}, {"model": "contenttypes.contenttype", "pk": 17, "fields": {"app_label": "property", "model": "fivereview"}}, {"model": "contenttypes.contenttype", "pk": 18, "fields": {"app_label": "property", "model": "detailedinfo"}}, {"model": "contenttypes.contenttype", "pk": 19, "fields": {"app_label": "property", "model": "customercare"}}, {"model": "users.customuser", "pk": 1, "fields": {"password": "pbkdf2_sha256$260000$pr5RcIsBqwEkBW0OJ8od29$z8txv7FHdZYx7wEB8BzAzkNzLOex5dV0ZhOYsk1lGgM=", "last_login": null, "is_superuser": true, "username": "Admin", "fullName": "", "phone": "+23469404088", "email": "admin@bethelhousing.com.ng", "accountType": "As a Staff", "is_staff": true, "is_active": true, "is_customer": true, "is_agent": true, "is_agency": true, "date_joined": "2023-01-29T13:47:03.110Z", "update_fields": "2023-01-29T13:47:03.408Z", "groups": [], "user_permissions": []}}, {"model": "users.customuser", "pk": 2, "fields": {"password": "pbkdf2_sha256$260000$5fC3OCpXZP0MoVw8Zc6ncm$4KN3g+pevk1R/2xWJtAjxGzxSG2oy1zT07SXfxvMxIU=", "last_login": null, "is_superuser": true, "username": "Support", "fullName": "", "phone": "+2348169404088", "email": "support@bethelhousing.com.ng", "accountType": "As a Staff", "is_staff": true, "is_active": true, "is_customer": true, "is_agent": true, "is_agency": true, "date_joined": "2023-01-29T13:49:54.797Z", "update_fields": "2023-01-29T13:49:55.042Z", "groups": [], "user_permissions": []}}, {"model": "users.customuser", "pk": 3, "fields": {"password": "pbkdf2_sha256$260000$7zGjebuqWl1cbP3cPblXjt$vkmMm/tAiv+289WAycG7EL8Ra9QmuHezTJ1z7bAj/Fc=", "last_login": null, "is_superuser": true, "username": "technical", "fullName": "", "phone": "+2349999999999", "email": "technical@bethelhousing.com.ng", "accountType": "As a Staff", "is_staff": true, "is_active": true, "is_customer": true, "is_agent": true, "is_agency": true, "date_joined": "2023-01-29T13:51:20.207Z", "update_fields": "2023-01-29T13:51:20.451Z", "groups": [], "user_permissions": []}}, {"model": "users.customuser", "pk": 4, "fields": {"password": "pbkdf2_sha256$260000$tmcSiAuRsMdmZo5lwtMdXH$Edn+Aiob0HVhRDle/QFuKGmXsir6LWQ2G+2xLv3Foqs=", "last_login": null, "is_superuser": true, "username": "info", "fullName": "", "phone": "+23400000099999", "email": "info@bethelhousing.com.ng", "accountType": "As a Staff", "is_staff": true, "is_active": true, "is_customer": true, "is_agent": true, "is_agency": true, "date_joined": "2023-01-29T13:52:25.838Z", "update_fields": "2023-01-29T13:52:26.087Z", "groups": [], "user_permissions": []}}, {"model": "property.uid", "pk": "1fc89ab6-5041-456d-ab87-fdd0e15aba60", "fields": {"basicInfo": false, "locationInfo": false, "imageFile": false, "detailedInfo": false, "contactInfo": false, "date_added": "2023-01-28T23:46:57.801Z"}}, {"model": "property.uid", "pk": "595e2279-d4b6-4ef2-8320-5823385ccd0a", "fields": {"basicInfo": false, "locationInfo": false, "imageFile": false, "detailedInfo": false, "contactInfo": false, "date_added": "2023-01-28T23:49:35.122Z"}}]